[
    {
        "id": 1,
        "title": "Task 1: Design Homepage",
        "description": "Create the design for the homepage of the website.",
        "status": "to-do"
    },
    {
        "id": 2,
        "title": "Task 2: Setup Database",
        "description": "Setup PostgreSQL database for the project.",
        "status": "in-progress"
    },
    {
        "id": 3,
        "title": "Task 3: Implement User Authentication",
        "description": "Implement user registration and login system with JWT authentication.",
        "status": "to-do"
    },
    {
        "id": 4,
        "title": "Task 4: Write API Documentation",
        "description": "Document the endpoints of the API for the project.",
        "status": "done"
    },
    {
        "id": 5,
        "title": "Task 5: Bug Fixing in Dashboard",
        "description": "Fix bugs related to the dashboard's data visualization.",
        "status": "in-progress"
    }
]
 